sv2svg/__init__.py
sv2svg/_version.py
sv2svg/cli.py
sv2svg/core.py
sv2svg/layout.py
sv2svg-0.11.4.dist-info/METADATA
sv2svg-0.11.4.dist-info/WHEEL
sv2svg-0.11.4.dist-info/entry_points.txt
sv2svg-0.11.4.dist-info/licenses/LICENSE
sv2svg-0.11.4.dist-info/RECORD
