Metadata-Version: 2.4
Name: sv2svg
Version: 0.11.4
Summary: SystemVerilog to SVG using Schemdraw (left-to-right logic diagrams)
Project-URL: Homepage, https://github.com/ErikMeinders/sv2svg
Project-URL: Repository, https://github.com/ErikMeinders/sv2svg
Project-URL: Issues, https://github.com/ErikMeinders/sv2svg/issues
Author: Erik
License: MIT
License-File: LICENSE
Requires-Python: >=3.9
Requires-Dist: schemdraw>=0.16
Provides-Extra: test
Requires-Dist: pytest-cov>=4.0; extra == 'test'
Requires-Dist: pytest>=7.0; extra == 'test'
